{
  "POIs": [
    {
      "fit": [
        -0.4181496202945709,
        0.7802962064743042,
        2.473212480545044
      ],
      "name": "r"
    }
  ],
  "method": "default",
  "params": [
    {
      "fit": [
        -0.33129608631134033,
        0.007536896038800478,
        0.34528088569641113
      ],
      "groups": [],
      "impact_r": 0.12122386693954468,
      "name": "DY",
      "prefit": [
        -0.9999999999999999,
        0.0,
        0.9999999999999999
      ],
      "r": [
        0.6591359972953796,
        0.7803598642349243,
        0.897271990776062
      ],
      "type": "Gaussian"
    },
    {
      "fit": [
        -0.9525336027145386,
        0.033090051263570786,
        1.0195436477661133
      ],
      "groups": [],
      "impact_r": 0.02030545473098755,
      "name": "DY_SR",
      "prefit": [
        -1.0,
        0.0,
        1.0
      ],
      "r": [
        0.8006203174591064,
        0.7803148627281189,
        0.7603376507759094
      ],
      "type": "Gaussian"
    },
    {
      "fit": [
        -0.9940637350082397,
        2.332083386136219e-05,
        0.9943954348564148
      ],
      "groups": [],
      "impact_r": 0.012778699398040771,
      "name": "FSmet",
      "prefit": [
        -1.0,
        0.0,
        1.0
      ],
      "r": [
        0.7930973172187805,
        0.7803186178207397,
        0.7679846882820129
      ],
      "type": "Gaussian"
    },
    {
      "fit": [
        -0.5186523795127869,
        0.01964222639799118,
        0.6701059341430664
      ],
      "groups": [],
      "impact_r": 0.06344771385192871,
      "name": "JEC",
      "prefit": [
        -1.0,
        0.0,
        1.0
      ],
      "r": [
        0.8267940282821655,
        0.7803016901016235,
        0.7168539762496948
      ],
      "type": "Gaussian"
    },
    {
      "fit": [
        -0.9774580001831055,
        -0.0013923386577516794,
        0.9759216904640198
      ],
      "groups": [],
      "impact_r": 0.01753288507461548,
      "name": "JER",
      "prefit": [
        -1.0,
        0.0,
        1.0
      ],
      "r": [
        0.7978695631027222,
        0.7803366780281067,
        0.7642503380775452
      ],
      "type": "Gaussian"
    },
    {
      "fit": [
        -0.9661489725112915,
        0.0010591325117275119,
        0.9670385718345642
      ],
      "groups": [],
      "impact_r": 0.02085632085800171,
      "name": "Lumi",
      "prefit": [
        -0.9999999999999999,
        0.0,
        0.9999999999999999
      ],
      "r": [
        0.8011887073516846,
        0.7803323864936829,
        0.7601029276847839
      ],
      "type": "Gaussian"
    },
    {
      "fit": [
        -0.9796572327613831,
        0.0013126209378242493,
        0.9830869436264038
      ],
      "groups": [],
      "impact_r": 0.0005099773406982422,
      "name": "PDF",
      "prefit": [
        -1.0,
        0.0,
        1.0
      ],
      "r": [
        0.7798706293106079,
        0.7803806066513062,
        0.7808242440223694
      ],
      "type": "Gaussian"
    },
    {
      "fit": [
        -0.8733381628990173,
        -0.10215821117162704,
        0.7004665732383728
      ],
      "groups": [],
      "impact_r": 0.0049613118171691895,
      "name": "PU",
      "prefit": [
        -1.0,
        0.0,
        1.0
      ],
      "r": [
        0.7762224674224854,
        0.7803337574005127,
        0.7852950692176819
      ],
      "type": "Gaussian"
    },
    {
      "fit": [
        -0.9940952062606812,
        -8.204190635296982e-06,
        0.9943802952766418
      ],
      "groups": [],
      "impact_r": 0.01273202896118164,
      "name": "PUFS",
      "prefit": [
        -1.0,
        0.0,
        1.0
      ],
      "r": [
        0.7930718660354614,
        0.7803398370742798,
        0.7679618000984192
      ],
      "type": "Gaussian"
    },
    {
      "fit": [
        -0.9470191597938538,
        0.02489367127418518,
        0.9984079599380493
      ],
      "groups": [],
      "impact_r": 0.014950871467590332,
      "name": "SFb",
      "prefit": [
        -1.0,
        0.0,
        1.0
      ],
      "r": [
        0.7952960729598999,
        0.7803452014923096,
        0.7661434412002563
      ],
      "type": "Gaussian"
    },
    {
      "fit": [
        -0.988826334476471,
        0.004485206212848425,
        0.9974190592765808
      ],
      "groups": [],
      "impact_r": 0.03535950183868408,
      "name": "SFl",
      "prefit": [
        -1.0,
        0.0,
        1.0
      ],
      "r": [
        0.8157249093055725,
        0.7803654074668884,
        0.746103048324585
      ],
      "type": "Gaussian"
    },
    {
      "fit": [
        -0.9941117167472839,
        -2.416027564322576e-05,
        0.9943720102310181
      ],
      "groups": [],
      "impact_r": 0.012620627880096436,
      "name": "btagFS",
      "prefit": [
        -1.0,
        0.0,
        1.0
      ],
      "r": [
        0.7929679155349731,
        0.7803472876548767,
        0.7678666114807129
      ],
      "type": "Gaussian"
    },
    {
      "fit": [
        -0.9941004514694214,
        -1.3350427252589725e-05,
        0.9943775534629822
      ],
      "groups": [],
      "impact_r": 0.02161175012588501,
      "name": "isr",
      "prefit": [
        -1.0,
        0.0,
        1.0
      ],
      "r": [
        0.8018754124641418,
        0.7802636623382568,
        0.7617684006690979
      ],
      "type": "Gaussian"
    },
    {
      "fit": [
        -0.9941117167472839,
        -2.416027564322576e-05,
        0.9943720102310181
      ],
      "groups": [],
      "impact_r": 0.012620747089385986,
      "name": "leptonFS",
      "prefit": [
        -1.0,
        0.0,
        1.0
      ],
      "r": [
        0.7929680347442627,
        0.7803472876548767,
        0.7678666114807129
      ],
      "type": "Gaussian"
    },
    {
      "fit": [
        -0.9549291729927063,
        -0.006974698044359684,
        0.9454429745674133
      ],
      "groups": [],
      "impact_r": 0.04538494348526001,
      "name": "leptonSF",
      "prefit": [
        -1.0,
        0.0,
        1.0
      ],
      "r": [
        0.8257139325141907,
        0.7803289890289307,
        0.7391716241836548
      ],
      "type": "Gaussian"
    },
    {
      "fit": [
        -0.3202890157699585,
        0.049750056117773056,
        0.4050908088684082
      ],
      "groups": [],
      "impact_r": 0.0038856863975524902,
      "name": "multiBoson",
      "prefit": [
        -0.9999999999999999,
        0.0,
        0.9999999999999999
      ],
      "r": [
        0.7842009663581848,
        0.7803152799606323,
        0.7820566892623901
      ],
      "type": "Gaussian"
    },
    {
      "fit": [
        -0.9389656782150269,
        -0.043057408183813095,
        0.8210609555244446
      ],
      "groups": [],
      "impact_r": 0.0332341194152832,
      "name": "other",
      "prefit": [
        -0.9999999999999999,
        0.0,
        0.9999999999999999
      ],
      "r": [
        0.8097389340400696,
        0.7803865075111389,
        0.7471523880958557
      ],
      "type": "Gaussian"
    },
    {
      "fit": [
        -0.9571421146392822,
        0.003579971846193075,
        0.9643591642379761
      ],
      "groups": [],
      "impact_r": 0.0014174580574035645,
      "name": "prop_binBin0_bin0",
      "prefit": [
        -0.9999999999999999,
        0.0,
        0.9999999999999999
      ],
      "r": [
        0.7817297577857971,
        0.7803122997283936,
        0.7790138125419617
      ],
      "type": "Gaussian"
    },
    {
      "fit": [
        -0.9646921753883362,
        -0.004075337201356888,
        0.9569241404533386
      ],
      "groups": [],
      "impact_r": 0.0013309121131896973,
      "name": "prop_binBin0_bin1",
      "prefit": [
        -0.9999999999999999,
        0.0,
        0.9999999999999999
      ],
      "r": [
        0.7792116403579712,
        0.780348539352417,
        0.7816794514656067
      ],
      "type": "Gaussian"
    },
    {
      "fit": [
        -0.6714708805084229,
        0.18296769261360168,
        1.092833161354065
      ],
      "groups": [],
      "impact_r": 0.012501239776611328,
      "name": "prop_binBin0_bin10",
      "prefit": [
        -0.9999999999999999,
        0.0,
        0.9999999999999999
      ],
      "r": [
        0.7678631544113159,
        0.7803643941879272,
        0.7867491841316223
      ],
      "type": "Gaussian"
    },
    {
      "fit": [
        -0.9802566170692444,
        -0.05472242087125778,
        0.8797748684883118
      ],
      "groups": [],
      "impact_r": 0.007258236408233643,
      "name": "prop_binBin0_bin11",
      "prefit": [
        -0.9999999999999999,
        0.0,
        0.9999999999999999
      ],
      "r": [
        0.7730487585067749,
        0.7803069949150085,
        0.7871416807174683
      ],
      "type": "Gaussian"
    },
    {
      "fit": [
        -0.836217999458313,
        -0.004443923942744732,
        0.8902909159660339
      ],
      "groups": [],
      "impact_r": 0.025416076183319092,
      "name": "prop_binBin0_bin12",
      "prefit": [
        -0.9999999999999999,
        0.0,
        0.9999999999999999
      ],
      "r": [
        0.7549562454223633,
        0.7803723216056824,
        0.7933022975921631
      ],
      "type": "Gaussian"
    },
    {
      "fit": [
        -0.9522168040275574,
        0.009649313054978848,
        0.9724398851394653
      ],
      "groups": [],
      "impact_r": 0.014416158199310303,
      "name": "prop_binBin0_bin13",
      "prefit": [
        -0.9999999999999999,
        0.0,
        0.9999999999999999
      ],
      "r": [
        0.7947495579719543,
        0.780333399772644,
        0.766755998134613
      ],
      "type": "Gaussian"
    },
    {
      "fit": [
        -0.8236305713653564,
        0.0882057175040245,
        1.0222309827804565
      ],
      "groups": [],
      "impact_r": 0.004728555679321289,
      "name": "prop_binBin0_bin14",
      "prefit": [
        -0.9999999999999999,
        0.0,
        0.9999999999999999
      ],
      "r": [
        0.7755948305130005,
        0.7803233861923218,
        0.7826554179191589
      ],
      "type": "Gaussian"
    },
    {
      "fit": [
        -0.950745701789856,
        -0.02488047629594803,
        0.905817449092865
      ],
      "groups": [],
      "impact_r": 0.0049394965171813965,
      "name": "prop_binBin0_bin15",
      "prefit": [
        -0.9999999999999999,
        0.0,
        0.9999999999999999
      ],
      "r": [
        0.7853214740753174,
        0.780381977558136,
        0.776397705078125
      ],
      "type": "Gaussian"
    },
    {
      "fit": [
        -0.880454421043396,
        0.026328256353735924,
        0.9503388404846191
      ],
      "groups": [],
      "impact_r": 0.027373015880584717,
      "name": "prop_binBin0_bin16",
      "prefit": [
        -0.9999999999999999,
        0.0,
        0.9999999999999999
      ],
      "r": [
        0.7529621124267578,
        0.7803351283073425,
        0.8015837669372559
      ],
      "type": "Gaussian"
    },
    {
      "fit": [
        -0.860245943069458,
        0.03779664263129234,
        0.9499067664146423
      ],
      "groups": [],
      "impact_r": 0.017585277557373047,
      "name": "prop_binBin0_bin17",
      "prefit": [
        -0.9999999999999999,
        0.0,
        0.9999999999999999
      ],
      "r": [
        0.7627066969871521,
        0.7802919745445251,
        0.7965839505195618
      ],
      "type": "Gaussian"
    },
    {
      "fit": [
        -0.909605085849762,
        0.012692967429757118,
        0.945504367351532
      ],
      "groups": [],
      "impact_r": 0.01794755458831787,
      "name": "prop_binBin0_bin18",
      "prefit": [
        -0.9999999999999999,
        0.0,
        0.9999999999999999
      ],
      "r": [
        0.7624484896659851,
        0.780396044254303,
        0.7964416146278381
      ],
      "type": "Gaussian"
    },
    {
      "fit": [
        -0.9676380157470703,
        -0.01611119508743286,
        0.9375182390213013
      ],
      "groups": [],
      "impact_r": 0.010200917720794678,
      "name": "prop_binBin0_bin19",
      "prefit": [
        -0.9999999999999999,
        0.0,
        0.9999999999999999
      ],
      "r": [
        0.790492832660675,
        0.7802919149398804,
        0.7716514468193054
      ],
      "type": "Gaussian"
    },
    {
      "fit": [
        -0.9588494896888733,
        0.004094382748007774,
        0.9687417149543762
      ],
      "groups": [],
      "impact_r": 0.00701749324798584,
      "name": "prop_binBin0_bin2",
      "prefit": [
        -0.9999999999999999,
        0.0,
        0.9999999999999999
      ],
      "r": [
        0.7733394503593445,
        0.7803569436073303,
        0.786677896976471
      ],
      "type": "Gaussian"
    },
    {
      "fit": [
        -0.9495366215705872,
        0.007806512992829084,
        0.9654711484909058
      ],
      "groups": [],
      "impact_r": 0.0005875229835510254,
      "name": "prop_binBin0_bin20",
      "prefit": [
        -0.9999999999999999,
        0.0,
        0.9999999999999999
      ],
      "r": [
        0.779798686504364,
        0.780386209487915,
        0.7808961272239685
      ],
      "type": "Gaussian"
    },
    {
      "fit": [
        -0.9604508876800537,
        0.002730726031586528,
        0.9668984413146973
      ],
      "groups": [],
      "impact_r": 0.00023549795150756836,
      "name": "prop_binBin0_bin21",
      "prefit": [
        -0.9999999999999999,
        0.0,
        0.9999999999999999
      ],
      "r": [
        0.7801395058631897,
        0.7803112864494324,
        0.7805467844009399
      ],
      "type": "Gaussian"
    },
    {
      "fit": [
        -0.8167191743850708,
        0.08869878202676773,
        1.026023507118225
      ],
      "groups": [],
      "impact_r": 0.002493143081665039,
      "name": "prop_binBin0_bin22",
      "prefit": [
        -0.9999999999999999,
        0.0,
        0.9999999999999999
      ],
      "r": [
        0.7778626084327698,
        0.7803557515144348,
        0.780357837677002
      ],
      "type": "Gaussian"
    },
    {
      "fit": [
        -1.1065456867218018,
        -0.11167352646589279,
        0.8827682733535767
      ],
      "groups": [],
      "impact_r": 7.212162017822266e-06,
      "name": "prop_binBin0_bin23",
      "prefit": [
        -0.9999999999999999,
        0.0,
        0.9999999999999999
      ],
      "r": [
        0.7803297638893127,
        0.7803230881690979,
        0.7803303003311157
      ],
      "type": "Gaussian"
    },
    {
      "fit": [
        -0.954765796661377,
        -0.0003174143494106829,
        0.9551675319671631
      ],
      "groups": [],
      "impact_r": 0.003269493579864502,
      "name": "prop_binBin0_bin24",
      "prefit": [
        -0.9999999999999999,
        0.0,
        0.9999999999999999
      ],
      "r": [
        0.7770563960075378,
        0.7802959680557251,
        0.7835654616355896
      ],
      "type": "Gaussian"
    },
    {
      "fit": [
        -0.9595849514007568,
        -0.0005992793594487011,
        0.9592136740684509
      ],
      "groups": [],
      "impact_r": 0.0004189610481262207,
      "name": "prop_binBin0_bin25",
      "prefit": [
        -0.9999999999999999,
        0.0,
        0.9999999999999999
      ],
      "r": [
        0.7800183296203613,
        0.7803322076797485,
        0.7807511687278748
      ],
      "type": "Gaussian"
    },
    {
      "fit": [
        -1.147238850593567,
        -0.15324483811855316,
        0.8412277102470398
      ],
      "groups": [],
      "impact_r": 7.987022399902344e-06,
      "name": "prop_binBin0_bin26",
      "prefit": [
        -0.9999999999999999,
        0.0,
        0.9999999999999999
      ],
      "r": [
        0.780379056930542,
        0.7803864479064941,
        0.7803784608840942
      ],
      "type": "Gaussian"
    },
    {
      "fit": [
        -0.7952551245689392,
        0.13202521204948425,
        1.0811638832092285
      ],
      "groups": [],
      "impact_r": 0.0071683526039123535,
      "name": "prop_binBin0_bin27",
      "prefit": [
        -0.9999999999999999,
        0.0,
        0.9999999999999999
      ],
      "r": [
        0.7875323295593262,
        0.7803639769554138,
        0.7765992879867554
      ],
      "type": "Gaussian"
    },
    {
      "fit": [
        -0.9427962899208069,
        -0.002029786352068186,
        0.9482219219207764
      ],
      "groups": [],
      "impact_r": 0.01257932186126709,
      "name": "prop_binBin0_bin28",
      "prefit": [
        -0.9999999999999999,
        0.0,
        0.9999999999999999
      ],
      "r": [
        0.7929660081863403,
        0.7803866863250732,
        0.7737712264060974
      ],
      "type": "Gaussian"
    },
    {
      "fit": [
        -0.9655836820602417,
        -0.004906763788312674,
        0.9606198072433472
      ],
      "groups": [],
      "impact_r": 0.010958254337310791,
      "name": "prop_binBin0_bin29",
      "prefit": [
        -0.9999999999999999,
        0.0,
        0.9999999999999999
      ],
      "r": [
        0.7912966012954712,
        0.7803383469581604,
        0.7713573575019836
      ],
      "type": "Gaussian"
    },
    {
      "fit": [
        -0.9760047197341919,
        0.004800588823854923,
        0.9865190386772156
      ],
      "groups": [],
      "impact_r": 0.009071648120880127,
      "name": "prop_binBin0_bin3",
      "prefit": [
        -0.9999999999999999,
        0.0,
        0.9999999999999999
      ],
      "r": [
        0.7712816596031189,
        0.780353307723999,
        0.7894185185432434
      ],
      "type": "Gaussian"
    },
    {
      "fit": [
        -1.0940492153167725,
        -0.09937035292387009,
        0.8950846195220947
      ],
      "groups": [],
      "impact_r": 0.007051408290863037,
      "name": "prop_binBin0_bin30",
      "prefit": [
        -0.9999999999999999,
        0.0,
        0.9999999999999999
      ],
      "r": [
        0.7874040603637695,
        0.7803526520729065,
        0.7733450531959534
      ],
      "type": "Gaussian"
    },
    {
      "fit": [
        -1.0740834474563599,
        -0.07950257509946823,
        0.9150362014770508
      ],
      "groups": [],
      "impact_r": 0.006232321262359619,
      "name": "prop_binBin0_bin31",
      "prefit": [
        -0.9999999999999999,
        0.0,
        0.9999999999999999
      ],
      "r": [
        0.7866469025611877,
        0.7804145812988281,
        0.7743232250213623
      ],
      "type": "Gaussian"
    },
    {
      "fit": [
        -0.859346866607666,
        0.0783560574054718,
        1.0272399187088013
      ],
      "groups": [],
      "impact_r": 0.0035086870193481445,
      "name": "prop_binBin0_bin32",
      "prefit": [
        -0.9999999999999999,
        0.0,
        0.9999999999999999
      ],
      "r": [
        0.7814303636550903,
        0.7803328633308411,
        0.7838415503501892
      ],
      "type": "Gaussian"
    },
    {
      "fit": [
        -0.9743219017982483,
        -0.07055254280567169,
        0.8579453229904175
      ],
      "groups": [],
      "impact_r": 0.005529284477233887,
      "name": "prop_binBin0_bin33",
      "prefit": [
        -0.9999999999999999,
        0.0,
        0.9999999999999999
      ],
      "r": [
        0.7748722434043884,
        0.7804015278816223,
        0.7838509678840637
      ],
      "type": "Gaussian"
    },
    {
      "fit": [
        -1.0152294635772705,
        -0.020325010642409325,
        0.9741501212120056
      ],
      "groups": [],
      "impact_r": 1.4781951904296875e-05,
      "name": "prop_binBin0_bin34",
      "prefit": [
        -0.9999999999999999,
        0.0,
        0.9999999999999999
      ],
      "r": [
        0.7803437113761902,
        0.780329704284668,
        0.7803444862365723
      ],
      "type": "Gaussian"
    },
    {
      "fit": [
        -1.010730266571045,
        -0.01572476141154766,
        0.9787195324897766
      ],
      "groups": [],
      "impact_r": 9.5367431640625e-07,
      "name": "prop_binBin0_bin35",
      "prefit": [
        -0.9999999999999999,
        0.0,
        0.9999999999999999
      ],
      "r": [
        0.7803343534469604,
        0.7803353071212769,
        0.7803343534469604
      ],
      "type": "Gaussian"
    },
    {
      "fit": [
        -0.9090482592582703,
        0.0358448401093483,
        0.9884499907493591
      ],
      "groups": [],
      "impact_r": 0.0008338689804077148,
      "name": "prop_binBin0_bin36",
      "prefit": [
        -0.9999999999999999,
        0.0,
        0.9999999999999999
      ],
      "r": [
        0.7811486721038818,
        0.7803148031234741,
        0.7798553109169006
      ],
      "type": "Gaussian"
    },
    {
      "fit": [
        -0.9379451870918274,
        0.017401279881596565,
        0.9782854914665222
      ],
      "groups": [],
      "impact_r": 0.001007676124572754,
      "name": "prop_binBin0_bin37",
      "prefit": [
        -0.9999999999999999,
        0.0,
        0.9999999999999999
      ],
      "r": [
        0.7812567949295044,
        0.7803506851196289,
        0.7793430089950562
      ],
      "type": "Gaussian"
    },
    {
      "fit": [
        -1.0281474590301514,
        -0.03367938473820686,
        0.9608057141304016
      ],
      "groups": [],
      "impact_r": 1.2814998626708984e-05,
      "name": "prop_binBin0_bin38",
      "prefit": [
        -0.9999999999999999,
        0.0,
        0.9999999999999999
      ],
      "r": [
        0.7803613543510437,
        0.7803494930267334,
        0.7803623080253601
      ],
      "type": "Gaussian"
    },
    {
      "fit": [
        -1.0212633609771729,
        -0.027257772162556648,
        0.9672200679779053
      ],
      "groups": [],
      "impact_r": 2.110004425048828e-05,
      "name": "prop_binBin0_bin39",
      "prefit": [
        -0.9999999999999999,
        0.0,
        0.9999999999999999
      ],
      "r": [
        0.7803465723991394,
        0.7803276181221008,
        0.7803487181663513
      ],
      "type": "Gaussian"
    },
    {
      "fit": [
        -0.9852480888366699,
        0.0040011233650147915,
        0.9934190511703491
      ],
      "groups": [],
      "impact_r": 0.0010483860969543457,
      "name": "prop_binBin0_bin4",
      "prefit": [
        -0.9999999999999999,
        0.0,
        0.9999999999999999
      ],
      "r": [
        0.7793047428131104,
        0.7803531289100647,
        0.7813970446586609
      ],
      "type": "Gaussian"
    },
    {
      "fit": [
        -1.019868016242981,
        -0.03477087244391441,
        0.9519174695014954
      ],
      "groups": [],
      "impact_r": 0.03336286544799805,
      "name": "prop_binBin0_bin40",
      "prefit": [
        -0.9999999999999999,
        0.0,
        0.9999999999999999
      ],
      "r": [
        0.8136382102966309,
        0.7802753448486328,
        0.7498818635940552
      ],
      "type": "Gaussian"
    },
    {
      "fit": [
        -0.9942965507507324,
        -0.019747883081436157,
        0.9592075347900391
      ],
      "groups": [],
      "impact_r": 0.022242367267608643,
      "name": "prop_binBin0_bin41",
      "prefit": [
        -0.9999999999999999,
        0.0,
        0.9999999999999999
      ],
      "r": [
        0.8026040196418762,
        0.7803616523742676,
        0.763161301612854
      ],
      "type": "Gaussian"
    },
    {
      "fit": [
        -0.9216914772987366,
        -0.013663041405379772,
        0.9234926104545593
      ],
      "groups": [],
      "impact_r": 0.17333585023880005,
      "name": "prop_binBin0_bin42",
      "prefit": [
        -0.9999999999999999,
        0.0,
        0.9999999999999999
      ],
      "r": [
        0.9537498950958252,
        0.7804140448570251,
        0.6942601799964905
      ],
      "type": "Gaussian"
    },
    {
      "fit": [
        -0.9709727168083191,
        0.01829521171748638,
        1.0090006589889526
      ],
      "groups": [],
      "impact_r": 0.03253495693206787,
      "name": "prop_binBin0_bin43",
      "prefit": [
        -0.9999999999999999,
        0.0,
        0.9999999999999999
      ],
      "r": [
        0.806486189365387,
        0.7803248167037964,
        0.7477898597717285
      ],
      "type": "Gaussian"
    },
    {
      "fit": [
        -0.9772841334342957,
        1.4264493074733764e-05,
        0.9799657464027405
      ],
      "groups": [],
      "impact_r": 0.2343827486038208,
      "name": "prop_binBin0_bin44",
      "prefit": [
        -0.9999999999999999,
        0.0,
        0.9999999999999999
      ],
      "r": [
        1.0147614479064941,
        0.7803786993026733,
        0.5903774499893188
      ],
      "type": "Gaussian"
    },
    {
      "fit": [
        -0.9544181823730469,
        0.020424727350473404,
        0.9982562065124512
      ],
      "groups": [],
      "impact_r": 0.2231845259666443,
      "name": "prop_binBin0_bin45",
      "prefit": [
        -0.9999999999999999,
        0.0,
        0.9999999999999999
      ],
      "r": [
        1.0035020112991333,
        0.780317485332489,
        0.6038514971733093
      ],
      "type": "Gaussian"
    },
    {
      "fit": [
        -0.9907439947128296,
        -0.005519043654203415,
        0.9799047112464905
      ],
      "groups": [],
      "impact_r": 0.007288098335266113,
      "name": "prop_binBin0_bin5",
      "prefit": [
        -0.9999999999999999,
        0.0,
        0.9999999999999999
      ],
      "r": [
        0.773070752620697,
        0.7803588509559631,
        0.7876234650611877
      ],
      "type": "Gaussian"
    },
    {
      "fit": [
        -0.9846263527870178,
        0.006504711229354143,
        0.9971972703933716
      ],
      "groups": [],
      "impact_r": 0.005651295185089111,
      "name": "prop_binBin0_bin6",
      "prefit": [
        -0.9999999999999999,
        0.0,
        0.9999999999999999
      ],
      "r": [
        0.7747891545295715,
        0.7804404497146606,
        0.7859528660774231
      ],
      "type": "Gaussian"
    },
    {
      "fit": [
        -0.9630236625671387,
        0.006231033708900213,
        0.9779328107833862
      ],
      "groups": [],
      "impact_r": 0.023874521255493164,
      "name": "prop_binBin0_bin7",
      "prefit": [
        -0.9999999999999999,
        0.0,
        0.9999999999999999
      ],
      "r": [
        0.7564534544944763,
        0.7803279757499695,
        0.8038005828857422
      ],
      "type": "Gaussian"
    },
    {
      "fit": [
        -0.8119995594024658,
        -0.09921729564666748,
        0.7365314364433289
      ],
      "groups": [],
      "impact_r": 0.0015426874160766602,
      "name": "prop_binBin0_bin8",
      "prefit": [
        -0.9999999999999999,
        0.0,
        0.9999999999999999
      ],
      "r": [
        0.7791064381599426,
        0.7803776264190674,
        0.7788349390029907
      ],
      "type": "Gaussian"
    },
    {
      "fit": [
        -0.9704822301864624,
        -0.04700924828648567,
        0.8819178938865662
      ],
      "groups": [],
      "impact_r": 0.007819116115570068,
      "name": "prop_binBin0_bin9",
      "prefit": [
        -0.9999999999999999,
        0.0,
        0.9999999999999999
      ],
      "r": [
        0.7724957466125488,
        0.7803148627281189,
        0.7858554124832153
      ],
      "type": "Gaussian"
    },
    {
      "fit": [
        -0.9941201210021973,
        -3.2083375117508695e-05,
        0.9943677186965942
      ],
      "groups": [],
      "impact_r": 0.012616157531738281,
      "name": "scale",
      "prefit": [
        -1.0,
        0.0,
        1.0
      ],
      "r": [
        0.7929807305335999,
        0.7803645730018616,
        0.7678797245025635
      ],
      "type": "Gaussian"
    },
    {
      "fit": [
        -0.9850230813026428,
        0.0005519395926967263,
        0.985549807548523
      ],
      "groups": [],
      "impact_r": 0.0005446672439575195,
      "name": "scaleTT",
      "prefit": [
        -1.0,
        0.0,
        1.0
      ],
      "r": [
        0.7798768877983093,
        0.7804215550422668,
        0.7808201313018799
      ],
      "type": "Gaussian"
    },
    {
      "fit": [
        -0.9895780086517334,
        0.0008255100692622364,
        0.99176424741745
      ],
      "groups": [],
      "impact_r": 0.0001061558723449707,
      "name": "scaleTTZ",
      "prefit": [
        -1.0,
        0.0,
        1.0
      ],
      "r": [
        0.7804702520370483,
        0.7803640961647034,
        0.780415952205658
      ],
      "type": "Gaussian"
    },
    {
      "fit": [
        -0.9564948081970215,
        0.010725277476012707,
        0.9792938828468323
      ],
      "groups": [],
      "impact_r": 0.005731701850891113,
      "name": "topFakes",
      "prefit": [
        -1.0,
        0.0,
        1.0
      ],
      "r": [
        0.786051332950592,
        0.7803196310997009,
        0.7748427987098694
      ],
      "type": "Gaussian"
    },
    {
      "fit": [
        -0.8446924090385437,
        0.019222598522901535,
        0.8875696063041687
      ],
      "groups": [],
      "impact_r": 0.002302408218383789,
      "name": "topGaus",
      "prefit": [
        -1.0,
        0.0,
        1.0
      ],
      "r": [
        0.7782154083251953,
        0.7803184986114502,
        0.782620906829834
      ],
      "type": "Gaussian"
    },
    {
      "fit": [
        -0.5805651545524597,
        0.040416885167360306,
        0.6895684599876404
      ],
      "groups": [],
      "impact_r": 0.0022531747817993164,
      "name": "topNonGaus",
      "prefit": [
        -1.0,
        0.0,
        1.0
      ],
      "r": [
        0.7825682759284973,
        0.780315101146698,
        0.7782078385353088
      ],
      "type": "Gaussian"
    },
    {
      "fit": [
        -0.2575816214084625,
        0.0029258565045893192,
        0.26632440090179443
      ],
      "groups": [],
      "impact_r": 0.012549221515655518,
      "name": "topNorm",
      "prefit": [
        -0.9999999999999999,
        0.0,
        0.9999999999999999
      ],
      "r": [
        0.7678096890449524,
        0.7803589105606079,
        0.7928216457366943
      ],
      "type": "Gaussian"
    },
    {
      "fit": [
        -0.9878709316253662,
        -0.0009074698318727314,
        0.9860836863517761
      ],
      "groups": [],
      "impact_r": 0.00070953369140625,
      "name": "topPt",
      "prefit": [
        -1.0,
        0.0,
        1.0
      ],
      "r": [
        0.7809432744979858,
        0.7803805470466614,
        0.7796710133552551
      ],
      "type": "Gaussian"
    },
    {
      "fit": [
        -1.0014244318008423,
        -0.010895275510847569,
        0.9792289137840271
      ],
      "groups": [],
      "impact_r": 0.0003204941749572754,
      "name": "trigger",
      "prefit": [
        -1.0,
        0.0,
        1.0
      ],
      "r": [
        0.7805153131484985,
        0.7802753448486328,
        0.7799548506736755
      ],
      "type": "Gaussian"
    },
    {
      "fit": [
        -0.6233734488487244,
        0.00783560425043106,
        0.6194083094596863
      ],
      "groups": [],
      "impact_r": 0.0010941624641418457,
      "name": "ttZ",
      "prefit": [
        -0.9999999999999999,
        0.0,
        0.9999999999999999
      ],
      "r": [
        0.7792356014251709,
        0.7803297638893127,
        0.7794761657714844
      ],
      "type": "Gaussian"
    },
    {
      "fit": [
        -1.0732964277267456,
        -0.09387681633234024,
        0.8869001269340515
      ],
      "groups": [],
      "impact_r": 0.20724397897720337,
      "name": "ttZ_SR",
      "prefit": [
        -1.0,
        0.0,
        1.0
      ],
      "r": [
        0.9875905513763428,
        0.7803465723991394,
        0.5864808559417725
      ],
      "type": "Gaussian"
    },
    {
      "fit": [
        -0.7575713992118835,
        -0.054361410439014435,
        0.6961727142333984
      ],
      "groups": [],
      "impact_r": 0.08690589666366577,
      "name": "unclEn",
      "prefit": [
        -1.0,
        0.0,
        1.0
      ],
      "r": [
        0.8672477602958679,
        0.7803418636322021,
        0.698427677154541
      ],
      "type": "Gaussian"
    }
  ]
}